PyMsOfa/__init__.py
PyMsOfa/cffi.py
PyMsOfa/cffi_t.py
PyMsOfa/ctypes.py
PyMsOfa/ctypes_t.py
PyMsOfa/libsofa_c.cp39-win_amd64.pyd
PyMsOfa/python.py
PyMsOfa/python_t.py
PyMsOfa-1.1.5.dist-info/LICENSE
PyMsOfa-1.1.5.dist-info/METADATA
PyMsOfa-1.1.5.dist-info/WHEEL
PyMsOfa-1.1.5.dist-info/top_level.txt
PyMsOfa-1.1.5.dist-info/RECORD
